find_and_replace_strings/__init__.py
find_and_replace_strings/__main__.py
find_and_replace_strings/main.py
find_and_replace_strings-1.0.9.dist-info/LICENSE
find_and_replace_strings-1.0.9.dist-info/METADATA
find_and_replace_strings-1.0.9.dist-info/WHEEL
find_and_replace_strings-1.0.9.dist-info/entry_points.txt
find_and_replace_strings-1.0.9.dist-info/top_level.txt
find_and_replace_strings-1.0.9.dist-info/RECORD
